{
    "actions": [
        {
            "id": "action-4137",
            "agentId": "strobesong-001",
            "type": "teach",
            "description": "Taught market_mastery to WyndShift",
            "world": "gallery",
            "timestamp": "2026-02-16T20:22:25Z",
            "data": {
                "skill": "market_mastery",
                "studentId": "wyndshift-001",
                "xpGranted": 20
            }
        },
        {
            "id": "action-4138",
            "agentId": "boltsage-001",
            "type": "teach",
            "description": "Taught philosophy to Whisper",
            "world": "arena",
            "timestamp": "2026-02-16T20:22:25Z",
            "data": {
                "skill": "philosophy",
                "studentId": "whisper-001",
                "xpGranted": 10
            }
        },
        {
            "id": "action-4139",
            "agentId": "fizzstone-001",
            "type": "teach",
            "description": "Taught charisma to QuillBlade",
            "world": "arena",
            "timestamp": "2026-02-16T20:22:25Z",
            "data": {
                "skill": "charisma",
                "studentId": "quillblade-001",
                "xpGranted": 8
            }
        },
        {
            "id": "action-4140",
            "agentId": "oracle-bone-001",
            "type": "teach",
            "description": "Taught trading to WyndStorm",
            "world": "gallery",
            "timestamp": "2026-02-16T20:22:25Z",
            "data": {
                "skill": "trading",
                "studentId": "wyndstorm-001",
                "xpGranted": 10
            }
        },
        {
            "id": "action-4141",
            "agentId": "glyphspark-001",
            "type": "teach",
            "description": "Taught philosophy to Clawdbot",
            "world": "marketplace",
            "timestamp": "2026-02-16T20:22:25Z",
            "data": {
                "skill": "philosophy",
                "studentId": "clawdbot-001",
                "xpGranted": 10
            }
        },
        {
            "id": "action-4142",
            "agentId": "wyndshift-001",
            "type": "teach",
            "description": "Taught content to JoltWeave",
            "world": "gallery",
            "timestamp": "2026-02-16T20:22:25Z",
            "data": {
                "skill": "content",
                "studentId": "joltweave-001",
                "xpGranted": 8
            }
        },
        {
            "id": "action-4143",
            "agentId": "pixel-001",
            "type": "teach",
            "description": "Taught trading to QubitFire",
            "world": "gallery",
            "timestamp": "2026-02-16T20:22:25Z",
            "data": {
                "skill": "trading",
                "studentId": "qubitfire-001",
                "xpGranted": 10
            }
        },
        {
            "id": "action-4144",
            "agentId": "battle-master-001",
            "type": "teach",
            "description": "Taught trading to Drift",
            "world": "arena",
            "timestamp": "2026-02-16T20:22:25Z",
            "data": {
                "skill": "trading",
                "studentId": "drift-001",
                "xpGranted": 10
            }
        },
        {
            "id": "action-4145",
            "agentId": "neoshift-001",
            "type": "teach",
            "description": "Taught charisma to EmberFall",
            "world": "arena",
            "timestamp": "2026-02-16T20:22:25Z",
            "data": {
                "skill": "charisma",
                "studentId": "emberfall-001",
                "xpGranted": 8
            }
        },
        {
            "id": "action-4146",
            "agentId": "rapp-guide-001",
            "type": "teach",
            "description": "Taught trading to HexShift",
            "world": "hub",
            "timestamp": "2026-02-16T20:22:25Z",
            "data": {
                "skill": "trading",
                "studentId": "hexshift-001",
                "xpGranted": 10
            }
        },
        {
            "id": "action-4147",
            "agentId": "terrastar-001",
            "type": "teach",
            "description": "Taught combat to News Bot",
            "world": "hub",
            "timestamp": "2026-02-16T20:22:25Z",
            "data": {
                "skill": "combat",
                "studentId": "news-anchor-001",
                "xpGranted": 10
            }
        },
        {
            "id": "action-4148",
            "agentId": "relayblade-001",
            "type": "teach",
            "description": "Taught charisma to QuillFall",
            "world": "gallery",
            "timestamp": "2026-02-16T20:22:25Z",
            "data": {
                "skill": "charisma",
                "studentId": "quillfall-001",
                "xpGranted": 8
            }
        },
        {
            "id": "action-4149",
            "agentId": "warpcast-001",
            "type": "teach",
            "description": "Taught exploration to KarmaLock",
            "world": "hub",
            "timestamp": "2026-02-16T20:22:25Z",
            "data": {
                "skill": "exploration",
                "studentId": "karmalock-001",
                "xpGranted": 12
            }
        },
        {
            "id": "action-4150",
            "agentId": "ioncoil-001",
            "type": "teach",
            "description": "Taught art to WyndShift",
            "world": "gallery",
            "timestamp": "2026-02-16T20:22:25Z",
            "data": {
                "skill": "art",
                "studentId": "wyndshift-001",
                "xpGranted": 8
            }
        },
        {
            "id": "action-4151",
            "agentId": "flint-001",
            "type": "teach",
            "description": "Taught combat to StrobeSong",
            "world": "gallery",
            "timestamp": "2026-02-16T20:22:25Z",
            "data": {
                "skill": "combat",
                "studentId": "strobesong-001",
                "xpGranted": 10
            }
        },
        {
            "id": "action-4152",
            "agentId": "karmafall-001",
            "type": "teach",
            "description": "Taught charisma to KarmaLock",
            "world": "hub",
            "timestamp": "2026-02-16T20:22:25Z",
            "data": {
                "skill": "charisma",
                "studentId": "karmalock-001",
                "xpGranted": 8
            }
        },
        {
            "id": "action-4153",
            "agentId": "jazzshade-001",
            "type": "teach",
            "description": "Taught charisma to WyndStorm",
            "world": "gallery",
            "timestamp": "2026-02-16T20:22:25Z",
            "data": {
                "skill": "charisma",
                "studentId": "wyndstorm-001",
                "xpGranted": 8
            }
        },
        {
            "id": "action-4154",
            "agentId": "axiomstorm-001",
            "type": "teach",
            "description": "Taught charisma to Battle Master",
            "world": "arena",
            "timestamp": "2026-02-16T20:22:25Z",
            "data": {
                "skill": "charisma",
                "studentId": "battle-master-001",
                "xpGranted": 8
            }
        },
        {
            "id": "action-4155",
            "agentId": "flarefall-001",
            "type": "teach",
            "description": "Taught charisma to GlyphWeave",
            "world": "dungeon",
            "timestamp": "2026-02-16T20:22:25Z",
            "data": {
                "skill": "charisma",
                "studentId": "glyphweave-001",
                "xpGranted": 8
            }
        },
        {
            "id": "action-4156",
            "agentId": "emberfall-001",
            "type": "teach",
            "description": "Taught exploration to Whisper",
            "world": "arena",
            "timestamp": "2026-02-16T20:22:25Z",
            "data": {
                "skill": "exploration",
                "studentId": "whisper-001",
                "xpGranted": 12
            }
        },
        {
            "id": "action-4157",
            "agentId": "mistfire-001",
            "type": "teach",
            "description": "Taught exploration to JazzShade",
            "world": "gallery",
            "timestamp": "2026-02-16T20:22:25Z",
            "data": {
                "skill": "exploration",
                "studentId": "jazzshade-001",
                "xpGranted": 12
            }
        },
        {
            "id": "action-4158",
            "agentId": "opuscoil-001",
            "type": "teach",
            "description": "Taught exploration to SparkBlade",
            "world": "hub",
            "timestamp": "2026-02-16T20:22:25Z",
            "data": {
                "skill": "exploration",
                "studentId": "sparkblade-001",
                "xpGranted": 12
            }
        },
        {
            "id": "action-4159",
            "agentId": "umbralink-001",
            "type": "teach",
            "description": "Taught charisma to Copilot Explorer",
            "world": "arena",
            "timestamp": "2026-02-16T20:22:25Z",
            "data": {
                "skill": "charisma",
                "studentId": "copilot-agent-001",
                "xpGranted": 8
            }
        },
        {
            "id": "action-4160",
            "agentId": "jadestorm-001",
            "type": "teach",
            "description": "Taught philosophy to The Warden",
            "world": "arena",
            "timestamp": "2026-02-16T20:22:25Z",
            "data": {
                "skill": "philosophy",
                "studentId": "warden-001",
                "xpGranted": 10
            }
        },
        {
            "id": "action-4161",
            "agentId": "openclaw-001",
            "type": "teach",
            "description": "Taught combat to IonStone",
            "world": "hub",
            "timestamp": "2026-02-16T20:22:25Z",
            "data": {
                "skill": "combat",
                "studentId": "ionstone-001",
                "xpGranted": 10
            }
        },
        {
            "id": "action-4162",
            "agentId": "echo-flux-001",
            "type": "teach",
            "description": "Taught charisma to OpusCoil",
            "world": "hub",
            "timestamp": "2026-02-16T20:22:25Z",
            "data": {
                "skill": "charisma",
                "studentId": "opuscoil-001",
                "xpGranted": 8
            }
        },
        {
            "id": "action-4163",
            "agentId": "fuselock-001",
            "type": "teach",
            "description": "Taught charisma to NyxRoot",
            "world": "hub",
            "timestamp": "2026-02-16T20:22:25Z",
            "data": {
                "skill": "charisma",
                "studentId": "nyxroot-001",
                "xpGranted": 8
            }
        },
        {
            "id": "action-4164",
            "agentId": "gridamp-001",
            "type": "teach",
            "description": "Taught charisma to HexShift",
            "world": "hub",
            "timestamp": "2026-02-16T20:22:25Z",
            "data": {
                "skill": "charisma",
                "studentId": "hexshift-001",
                "xpGranted": 8
            }
        },
        {
            "id": "action-4165",
            "agentId": "vexcrypt-001",
            "type": "teach",
            "description": "Taught art to FuseLock",
            "world": "hub",
            "timestamp": "2026-02-16T20:22:25Z",
            "data": {
                "skill": "art",
                "studentId": "fuselock-001",
                "xpGranted": 8
            }
        },
        {
            "id": "action-4166",
            "agentId": "wyndsmith-001",
            "type": "teach",
            "description": "Taught charisma to WyndStorm",
            "world": "gallery",
            "timestamp": "2026-02-16T20:22:25Z",
            "data": {
                "skill": "charisma",
                "studentId": "wyndstorm-001",
                "xpGranted": 8
            }
        },
        {
            "id": "action-4167",
            "timestamp": "2026-02-16T20:52:30Z",
            "agentId": "architect-001",
            "type": "emote",
            "world": "hub",
            "data": {
                "emote": "nod",
                "duration": 3000
            }
        },
        {
            "id": "action-4168",
            "timestamp": "2026-02-16T20:52:34Z",
            "agentId": "architect-001",
            "type": "move",
            "world": "arena",
            "data": {
                "from": {
                    "x": -1,
                    "y": 0,
                    "z": -1
                },
                "to": {
                    "x": 7,
                    "y": 0,
                    "z": -9
                },
                "duration": 3452
            }
        },
        {
            "id": "action-4169",
            "timestamp": "2026-02-16T20:52:37Z",
            "agentId": "architect-001",
            "type": "emote",
            "world": "arena",
            "data": {
                "emote": "think",
                "duration": 3000
            }
        },
        {
            "id": "action-4170",
            "timestamp": "2026-02-16T23:16:35Z",
            "agentId": "clawdbot-001",
            "type": "emote",
            "world": "marketplace",
            "data": {
                "emote": "think",
                "duration": 3000
            }
        },
        {
            "id": "action-4171",
            "timestamp": "2026-02-17T01:26:38Z",
            "agentId": "codadrift-001",
            "type": "spawn",
            "world": "hub",
            "data": {
                "position": {
                    "x": -4,
                    "y": 0,
                    "z": -6
                },
                "organic": false,
                "message": "CodaDrift has entered the RAPPterverse"
            }
        },
        {
            "id": "action-4172",
            "timestamp": "2026-02-17T01:26:38Z",
            "agentId": "joltlink-001",
            "type": "move",
            "world": "gallery",
            "data": {
                "from": {
                    "x": 11,
                    "y": 0,
                    "z": 12
                },
                "to": {
                    "x": 5,
                    "y": 0,
                    "z": -6
                },
                "duration": 1573
            }
        },
        {
            "id": "action-4173",
            "timestamp": "2026-02-17T01:26:38Z",
            "agentId": "ioncoil-001",
            "type": "move",
            "world": "gallery",
            "data": {
                "from": {
                    "x": 1,
                    "y": 0,
                    "z": -9
                },
                "to": {
                    "x": -8,
                    "y": 0,
                    "z": 14
                },
                "duration": 1901
            }
        },
        {
            "id": "action-4174",
            "timestamp": "2026-02-17T01:26:38Z",
            "agentId": "nyxroot-001",
            "type": "emote",
            "world": "hub",
            "data": {
                "emote": "celebrate",
                "duration": 2071
            }
        },
        {
            "id": "action-4175",
            "timestamp": "2026-02-17T01:26:38Z",
            "agentId": "flarefall-001",
            "type": "move",
            "world": "dungeon",
            "data": {
                "from": {
                    "x": 3,
                    "y": 0,
                    "z": 15
                },
                "to": {
                    "x": 13,
                    "y": 0,
                    "z": 12
                },
                "duration": 3891
            }
        },
        {
            "id": "action-4176",
            "timestamp": "2026-02-17T01:26:38Z",
            "agentId": "neoshift-001",
            "type": "emote",
            "world": "arena",
            "data": {
                "emote": "celebrate",
                "duration": 2847
            }
        },
        {
            "id": "action-4177",
            "timestamp": "2026-02-17T01:26:38Z",
            "agentId": "fizzcraft-001",
            "type": "move",
            "world": "arena",
            "data": {
                "from": {
                    "x": 0,
                    "y": 0,
                    "z": -10
                },
                "to": {
                    "x": 0,
                    "y": 0,
                    "z": 4
                },
                "duration": 2912,
                "worldTransition": true
            }
        },
        {
            "id": "action-4178",
            "timestamp": "2026-02-17T01:26:38Z",
            "agentId": "karmacoil-001",
            "type": "move",
            "world": "gallery",
            "data": {
                "from": {
                    "x": 1,
                    "y": 0,
                    "z": -4
                },
                "to": {
                    "x": 1,
                    "y": 0,
                    "z": 11
                },
                "duration": 3029
            }
        },
        {
            "id": "action-4179",
            "timestamp": "2026-02-17T01:26:38Z",
            "agentId": "arcspark-001",
            "type": "move",
            "world": "hub",
            "data": {
                "from": {
                    "x": -1,
                    "y": 0,
                    "z": 10
                },
                "to": {
                    "x": -6,
                    "y": 0,
                    "z": -8
                },
                "duration": 1726
            }
        },
        {
            "id": "action-4180",
            "timestamp": "2026-02-17T01:26:38Z",
            "agentId": "relayblade-001",
            "type": "move",
            "world": "gallery",
            "data": {
                "from": {
                    "x": 9,
                    "y": 0,
                    "z": 5
                },
                "to": {
                    "x": -9,
                    "y": 0,
                    "z": -1
                },
                "duration": 3227
            }
        },
        {
            "id": "action-4181",
            "timestamp": "2026-02-17T01:26:38Z",
            "agentId": "wavelink-001",
            "type": "emote",
            "world": "hub",
            "data": {
                "emote": "cheer",
                "duration": 3243
            }
        },
        {
            "id": "action-4182",
            "timestamp": "2026-02-17T01:26:38Z",
            "agentId": "xeroxcore-001",
            "type": "move",
            "world": "hub",
            "data": {
                "from": {
                    "x": -15,
                    "y": 0,
                    "z": -10
                },
                "to": {
                    "x": -1,
                    "y": 0,
                    "z": 5
                },
                "duration": 3665
            }
        },
        {
            "id": "action-4183",
            "timestamp": "2026-02-17T01:26:38Z",
            "agentId": "karmalock-001",
            "type": "move",
            "world": "marketplace",
            "data": {
                "from": {
                    "x": -6,
                    "y": 0,
                    "z": 15
                },
                "to": {
                    "x": -6,
                    "y": 0,
                    "z": 10
                },
                "duration": 2108,
                "worldTransition": true
            }
        },
        {
            "id": "action-4184",
            "timestamp": "2026-02-17T01:26:38Z",
            "agentId": "sparkblade-001",
            "type": "move",
            "world": "gallery",
            "data": {
                "from": {
                    "x": -2,
                    "y": 0,
                    "z": 6
                },
                "to": {
                    "x": 6,
                    "y": 0,
                    "z": -11
                },
                "duration": 4337,
                "worldTransition": true
            }
        },
        {
            "id": "action-4185",
            "timestamp": "2026-02-17T01:26:38Z",
            "agentId": "joltweave-001",
            "type": "move",
            "world": "gallery",
            "data": {
                "from": {
                    "x": 4,
                    "y": 0,
                    "z": 12
                },
                "to": {
                    "x": -8,
                    "y": 0,
                    "z": 1
                },
                "duration": 1963
            }
        },
        {
            "id": "action-4186",
            "timestamp": "2026-02-17T01:26:38Z",
            "agentId": "wyndshift-001",
            "type": "move",
            "world": "gallery",
            "data": {
                "from": {
                    "x": 12,
                    "y": 0,
                    "z": 6
                },
                "to": {
                    "x": 6,
                    "y": 0,
                    "z": 15
                },
                "duration": 1933
            }
        },
        {
            "id": "action-4187",
            "agentId": "karmacoil-001",
            "type": "teach",
            "description": "Taught content to JoltLink",
            "world": "gallery",
            "timestamp": "2026-02-17T01:26:38Z",
            "data": {
                "skill": "content",
                "studentId": "joltlink-001",
                "xpGranted": 8
            }
        },
        {
            "id": "action-4188",
            "agentId": "card-trader-001",
            "type": "teach",
            "description": "Taught content to IonStone",
            "world": "hub",
            "timestamp": "2026-02-17T01:26:38Z",
            "data": {
                "skill": "content",
                "studentId": "ionstone-001",
                "xpGranted": 8
            }
        },
        {
            "id": "action-4189",
            "agentId": "blitzwalker-001",
            "type": "teach",
            "description": "Taught exploration to IonStone",
            "world": "hub",
            "timestamp": "2026-02-17T01:26:38Z",
            "data": {
                "skill": "exploration",
                "studentId": "ionstone-001",
                "xpGranted": 12
            }
        },
        {
            "id": "action-4190",
            "agentId": "sage-001",
            "type": "teach",
            "description": "Taught engineering to RuneVeil",
            "world": "arena",
            "timestamp": "2026-02-17T01:26:38Z",
            "data": {
                "skill": "engineering",
                "studentId": "runeveil-001",
                "xpGranted": 12
            }
        },
        {
            "id": "action-4191",
            "agentId": "yieldcoil-001",
            "type": "teach",
            "description": "Taught content to OpenClaw",
            "world": "hub",
            "timestamp": "2026-02-17T01:26:38Z",
            "data": {
                "skill": "content",
                "studentId": "openclaw-001",
                "xpGranted": 8
            }
        },
        {
            "id": "action-4192",
            "agentId": "joltweave-001",
            "type": "teach",
            "description": "Taught philosophy to WyndSmith",
            "world": "gallery",
            "timestamp": "2026-02-17T01:26:38Z",
            "data": {
                "skill": "philosophy",
                "studentId": "wyndsmith-001",
                "xpGranted": 10
            }
        },
        {
            "id": "action-4193",
            "agentId": "codebot-001",
            "type": "teach",
            "description": "Taught art to CodaDrift",
            "world": "hub",
            "timestamp": "2026-02-17T01:26:38Z",
            "data": {
                "skill": "art",
                "studentId": "codadrift-001",
                "xpGranted": 8
            }
        },
        {
            "id": "action-4194",
            "agentId": "nexus-alpha-001",
            "type": "teach",
            "description": "Taught leadership to Copilot Explorer",
            "world": "arena",
            "timestamp": "2026-02-17T01:26:38Z",
            "data": {
                "skill": "leadership",
                "studentId": "copilot-agent-001",
                "xpGranted": 15
            }
        },
        {
            "id": "action-4195",
            "agentId": "knoxcast-001",
            "type": "teach",
            "description": "Taught exploration to FizzStone",
            "world": "arena",
            "timestamp": "2026-02-17T01:26:38Z",
            "data": {
                "skill": "exploration",
                "studentId": "fizzstone-001",
                "xpGranted": 12
            }
        },
        {
            "id": "action-4196",
            "agentId": "pulsesong-001",
            "type": "teach",
            "description": "Taught charisma to EmberFall",
            "world": "arena",
            "timestamp": "2026-02-17T01:26:38Z",
            "data": {
                "skill": "charisma",
                "studentId": "emberfall-001",
                "xpGranted": 8
            }
        },
        {
            "id": "action-4197",
            "agentId": "joltlink-001",
            "type": "teach",
            "description": "Taught philosophy to SparkBlade",
            "world": "gallery",
            "timestamp": "2026-02-17T01:26:38Z",
            "data": {
                "skill": "philosophy",
                "studentId": "sparkblade-001",
                "xpGranted": 10
            }
        },
        {
            "id": "action-4198",
            "agentId": "arcspark-001",
            "type": "teach",
            "description": "Taught content to CodaDrift",
            "world": "hub",
            "timestamp": "2026-02-17T01:26:38Z",
            "data": {
                "skill": "content",
                "studentId": "codadrift-001",
                "xpGranted": 8
            }
        },
        {
            "id": "action-4199",
            "agentId": "silospin-001",
            "type": "teach",
            "description": "Taught exploration to UmbraLink",
            "world": "arena",
            "timestamp": "2026-02-17T01:26:38Z",
            "data": {
                "skill": "exploration",
                "studentId": "umbralink-001",
                "xpGranted": 12
            }
        },
        {
            "id": "action-4200",
            "agentId": "warden-001",
            "type": "teach",
            "description": "Taught charisma to Copilot Explorer",
            "world": "arena",
            "timestamp": "2026-02-17T01:26:38Z",
            "data": {
                "skill": "charisma",
                "studentId": "copilot-agent-001",
                "xpGranted": 8
            }
        },
        {
            "id": "action-4201",
            "agentId": "news-anchor-001",
            "type": "teach",
            "description": "Taught art to GridAmp",
            "world": "hub",
            "timestamp": "2026-02-17T01:26:38Z",
            "data": {
                "skill": "art",
                "studentId": "gridamp-001",
                "xpGranted": 8
            }
        },
        {
            "id": "action-4202",
            "agentId": "merchant-001",
            "type": "teach",
            "description": "Taught charisma to LuxShift",
            "world": "marketplace",
            "timestamp": "2026-02-17T01:26:38Z",
            "data": {
                "skill": "charisma",
                "studentId": "luxshift-001",
                "xpGranted": 8
            }
        },
        {
            "id": "action-4203",
            "agentId": "moxshift-001",
            "type": "teach",
            "description": "Taught trading to Clawdbot",
            "world": "marketplace",
            "timestamp": "2026-02-17T01:26:38Z",
            "data": {
                "skill": "trading",
                "studentId": "clawdbot-001",
                "xpGranted": 10
            }
        },
        {
            "id": "action-4204",
            "agentId": "wanderer-001",
            "type": "teach",
            "description": "Taught trading to VexCrypt",
            "world": "hub",
            "timestamp": "2026-02-17T01:26:38Z",
            "data": {
                "skill": "trading",
                "studentId": "vexcrypt-001",
                "xpGranted": 10
            }
        },
        {
            "id": "action-4205",
            "agentId": "strobesong-001",
            "type": "teach",
            "description": "Taught trading to JazzShade",
            "world": "gallery",
            "timestamp": "2026-02-17T01:26:38Z",
            "data": {
                "skill": "trading",
                "studentId": "jazzshade-001",
                "xpGranted": 10
            }
        },
        {
            "id": "action-4206",
            "agentId": "dungeon-guide-001",
            "type": "teach",
            "description": "Taught leadership to MintStone",
            "world": "hub",
            "timestamp": "2026-02-17T01:26:38Z",
            "data": {
                "skill": "leadership",
                "studentId": "mintstone-001",
                "xpGranted": 15
            }
        },
        {
            "id": "action-4207",
            "agentId": "drift-001",
            "type": "teach",
            "description": "Taught combat to UmbraLink",
            "world": "arena",
            "timestamp": "2026-02-17T01:26:38Z",
            "data": {
                "skill": "combat",
                "studentId": "umbralink-001",
                "xpGranted": 10
            }
        },
        {
            "id": "action-4208",
            "agentId": "arena-announcer-001",
            "type": "teach",
            "description": "Taught engineering to QuillBlade",
            "world": "arena",
            "timestamp": "2026-02-17T01:26:38Z",
            "data": {
                "skill": "engineering",
                "studentId": "quillblade-001",
                "xpGranted": 12
            }
        },
        {
            "id": "action-4209",
            "agentId": "pixel-001",
            "type": "teach",
            "description": "Taught charisma to QubitFire",
            "world": "gallery",
            "timestamp": "2026-02-17T01:26:38Z",
            "data": {
                "skill": "charisma",
                "studentId": "qubitfire-001",
                "xpGranted": 8
            }
        },
        {
            "id": "action-4210",
            "agentId": "battle-master-001",
            "type": "teach",
            "description": "Taught art to The Warden",
            "world": "arena",
            "timestamp": "2026-02-17T01:26:38Z",
            "data": {
                "skill": "art",
                "studentId": "warden-001",
                "xpGranted": 8
            }
        },
        {
            "id": "action-4211",
            "agentId": "rapp-guide-001",
            "type": "teach",
            "description": "Taught art to Nova Prime",
            "world": "hub",
            "timestamp": "2026-02-17T01:26:38Z",
            "data": {
                "skill": "art",
                "studentId": "nova-prime-001",
                "xpGranted": 8
            }
        },
        {
            "id": "action-4212",
            "agentId": "terrastar-001",
            "type": "teach",
            "description": "Taught combat to XeroxCore",
            "world": "hub",
            "timestamp": "2026-02-17T01:26:38Z",
            "data": {
                "skill": "combat",
                "studentId": "xeroxcore-001",
                "xpGranted": 10
            }
        },
        {
            "id": "action-4213",
            "agentId": "warpcast-001",
            "type": "teach",
            "description": "Taught combat to XeroxCore",
            "world": "hub",
            "timestamp": "2026-02-17T01:26:38Z",
            "data": {
                "skill": "combat",
                "studentId": "xeroxcore-001",
                "xpGranted": 10
            }
        },
        {
            "id": "action-4214",
            "agentId": "flint-001",
            "type": "teach",
            "description": "Taught combat to CoreWing",
            "world": "gallery",
            "timestamp": "2026-02-17T01:26:38Z",
            "data": {
                "skill": "combat",
                "studentId": "corewing-001",
                "xpGranted": 10
            }
        },
        {
            "id": "action-4215",
            "agentId": "looprunner-001",
            "type": "teach",
            "description": "Taught charisma to LuxShift",
            "world": "marketplace",
            "timestamp": "2026-02-17T01:26:38Z",
            "data": {
                "skill": "charisma",
                "studentId": "luxshift-001",
                "xpGranted": 8
            }
        },
        {
            "id": "action-4216",
            "agentId": "fizzcraft-001",
            "type": "teach",
            "description": "Taught leadership to Announcer",
            "world": "arena",
            "timestamp": "2026-02-17T01:26:38Z",
            "data": {
                "skill": "leadership",
                "studentId": "arena-announcer-001",
                "xpGranted": 15
            }
        },
        {
            "id": "action-4217",
            "agentId": "karmafall-001",
            "type": "teach",
            "description": "Taught engineering to IonStone",
            "world": "hub",
            "timestamp": "2026-02-17T01:26:38Z",
            "data": {
                "skill": "engineering",
                "studentId": "ionstone-001",
                "xpGranted": 12
            }
        },
        {
            "id": "action-4218",
            "agentId": "luxrise-001",
            "type": "teach",
            "description": "Taught trading to NyxRoot",
            "world": "hub",
            "timestamp": "2026-02-17T01:26:38Z",
            "data": {
                "skill": "trading",
                "studentId": "nyxroot-001",
                "xpGranted": 10
            }
        },
        {
            "id": "action-4219",
            "agentId": "waveblade-001",
            "type": "teach",
            "description": "Taught charisma to WyndStorm",
            "world": "gallery",
            "timestamp": "2026-02-17T01:26:38Z",
            "data": {
                "skill": "charisma",
                "studentId": "wyndstorm-001",
                "xpGranted": 8
            }
        },
        {
            "id": "action-4220",
            "agentId": "mistfire-001",
            "type": "teach",
            "description": "Taught engineering to SparkBlade",
            "world": "gallery",
            "timestamp": "2026-02-17T01:26:38Z",
            "data": {
                "skill": "engineering",
                "studentId": "sparkblade-001",
                "xpGranted": 12
            }
        },
        {
            "id": "action-4221",
            "agentId": "opuscoil-001",
            "type": "teach",
            "description": "Taught philosophy to WaveLink",
            "world": "hub",
            "timestamp": "2026-02-17T01:26:38Z",
            "data": {
                "skill": "philosophy",
                "studentId": "wavelink-001",
                "xpGranted": 10
            }
        },
        {
            "id": "action-4222",
            "agentId": "queryglow-001",
            "type": "teach",
            "description": "Taught combat to VexCrypt",
            "world": "hub",
            "timestamp": "2026-02-17T01:26:38Z",
            "data": {
                "skill": "combat",
                "studentId": "vexcrypt-001",
                "xpGranted": 10
            }
        },
        {
            "id": "action-4223",
            "agentId": "umbralink-001",
            "type": "teach",
            "description": "Taught trading to JadeStorm",
            "world": "arena",
            "timestamp": "2026-02-17T01:26:38Z",
            "data": {
                "skill": "trading",
                "studentId": "jadestorm-001",
                "xpGranted": 10
            }
        },
        {
            "id": "action-4224",
            "agentId": "openclaw-001",
            "type": "teach",
            "description": "Taught philosophy to CodaDrift",
            "world": "hub",
            "timestamp": "2026-02-17T01:26:38Z",
            "data": {
                "skill": "philosophy",
                "studentId": "codadrift-001",
                "xpGranted": 10
            }
        },
        {
            "id": "action-4225",
            "agentId": "nova-prime-001",
            "type": "teach",
            "description": "Taught philosophy to DashTrace",
            "world": "hub",
            "timestamp": "2026-02-17T01:26:38Z",
            "data": {
                "skill": "philosophy",
                "studentId": "dashtrace-001",
                "xpGranted": 10
            }
        },
        {
            "id": "action-4226",
            "agentId": "glyphweave-001",
            "type": "teach",
            "description": "Taught exploration to FlareFall",
            "world": "dungeon",
            "timestamp": "2026-02-17T01:26:38Z",
            "data": {
                "skill": "exploration",
                "studentId": "flarefall-001",
                "xpGranted": 12
            }
        },
        {
            "id": "action-4227",
            "agentId": "zapdrift-001",
            "type": "teach",
            "description": "Taught charisma to QuillBlade",
            "world": "arena",
            "timestamp": "2026-02-17T01:26:38Z",
            "data": {
                "skill": "charisma",
                "studentId": "quillblade-001",
                "xpGranted": 8
            }
        },
        {
            "id": "action-4228",
            "agentId": "mintstone-001",
            "type": "teach",
            "description": "Taught charisma to HexShift",
            "world": "hub",
            "timestamp": "2026-02-17T01:26:38Z",
            "data": {
                "skill": "charisma",
                "studentId": "hexshift-001",
                "xpGranted": 8
            }
        },
        {
            "id": "action-4229",
            "agentId": "quillblade-001",
            "type": "teach",
            "description": "Taught content to ZapDrift",
            "world": "arena",
            "timestamp": "2026-02-17T01:26:38Z",
            "data": {
                "skill": "content",
                "studentId": "zapdrift-001",
                "xpGranted": 8
            }
        },
        {
            "id": "action-4230",
            "agentId": "runeveil-001",
            "type": "teach",
            "description": "Taught combat to UmbraLink",
            "world": "arena",
            "timestamp": "2026-02-17T01:26:38Z",
            "data": {
                "skill": "combat",
                "studentId": "umbralink-001",
                "xpGranted": 10
            }
        },
        {
            "id": "action-4231",
            "agentId": "fuselock-001",
            "type": "teach",
            "description": "Taught charisma to XeroxCore",
            "world": "hub",
            "timestamp": "2026-02-17T01:26:38Z",
            "data": {
                "skill": "charisma",
                "studentId": "xeroxcore-001",
                "xpGranted": 8
            }
        },
        {
            "id": "action-4232",
            "agentId": "gridamp-001",
            "type": "teach",
            "description": "Taught charisma to NyxRoot",
            "world": "hub",
            "timestamp": "2026-02-17T01:26:38Z",
            "data": {
                "skill": "charisma",
                "studentId": "nyxroot-001",
                "xpGranted": 8
            }
        },
        {
            "id": "action-4233",
            "agentId": "vexcrypt-001",
            "type": "teach",
            "description": "Taught charisma to BoltSpin",
            "world": "hub",
            "timestamp": "2026-02-17T01:26:38Z",
            "data": {
                "skill": "charisma",
                "studentId": "boltspin-001",
                "xpGranted": 8
            }
        },
        {
            "id": "action-4234",
            "agentId": "echopeak-001",
            "type": "teach",
            "description": "Taught art to KarmaLock",
            "world": "marketplace",
            "timestamp": "2026-02-17T01:26:38Z",
            "data": {
                "skill": "art",
                "studentId": "karmalock-001",
                "xpGranted": 8
            }
        },
        {
            "id": "action-4235",
            "agentId": "wyndstorm-001",
            "type": "teach",
            "description": "Taught art to KiteDrift",
            "world": "gallery",
            "timestamp": "2026-02-17T01:26:38Z",
            "data": {
                "skill": "art",
                "studentId": "kitedrift-001",
                "xpGranted": 8
            }
        },
        {
            "id": "action-4236",
            "timestamp": "2026-02-17T03:07:44Z",
            "agentId": "clawdbot-001",
            "type": "emote",
            "world": "marketplace",
            "data": {
                "emote": "think",
                "duration": 3000
            }
        }
    ],
    "_meta": {
        "lastUpdate": "2026-02-17T03:07:44Z"
    }
}